coresender/__init__.py
coresender/context.py
coresender/token.py
coresender/errors/__init__.py
coresender/http_error_handlers/__init__.py
coresender/requests/__init__.py
coresender/requests/core.py
coresender/requests/send.py
coresender/responses/__init__.py
coresender/responses/core.py
coresender/responses/send.py
tests/__init__.py
tests/conftest.py
tests/test_errors.py
tests/test_init.py
tests/test_sending.py
coresender-1.1.1.dist-info/LICENSE
coresender-1.1.1.dist-info/METADATA
coresender-1.1.1.dist-info/WHEEL
coresender-1.1.1.dist-info/top_level.txt
coresender-1.1.1.dist-info/RECORD
