Metadata-Version: 2.1
Name: coresender
Version: 1.1.1
Summary: Coresender API for sending email
Home-page: https://coresender.com
Author: Marcin Sztolcman
Author-email: opensource@coresender.com
License: MIT
Project-URL: API Documentation, https://coresender.com/docs/api
Project-URL: Source, https://github.com/coresender/coresender-sdk-py
Keywords: coresender api email smtp mta transactional
Platform: UNKNOWN
Classifier: Development Status :: 5 - Production/Stable
Classifier: Intended Audience :: Developers
Classifier: Intended Audience :: Information Technology
Classifier: License :: OSI Approved :: MIT License
Classifier: Programming Language :: Python
Classifier: Programming Language :: Python :: 3
Classifier: Programming Language :: Python :: 3.6
Classifier: Programming Language :: Python :: 3.7
Classifier: Programming Language :: Python :: 3.8
Classifier: Programming Language :: Python :: Implementation :: CPython
Classifier: Programming Language :: Python :: Implementation :: PyPy
Classifier: Topic :: Communications :: Email
Classifier: Topic :: Communications :: Email :: Mail Transport Agents
Classifier: Environment :: Web Environment
Requires-Python: >=3.6
Requires-Dist: httpx (==0.12.0)
